{"frames": {

"03_HowToHost_Banner_01.png":
{
	"frame": {"x":1004,"y":0,"w":896,"h":896},
	"rotated": false,
	"trimmed": false,
	"spriteSourceSize": {"x":0,"y":0,"w":896,"h":896},
	"sourceSize": {"w":896,"h":896}
},
"03_HowToHost_Banner_02.png":
{
	"frame": {"x":1900,"y":0,"w":896,"h":896},
	"rotated": false,
	"trimmed": false,
	"spriteSourceSize": {"x":0,"y":0,"w":896,"h":896},
	"sourceSize": {"w":896,"h":896}
},
"03_HowToHost_Banner_03.png":
{
	"frame": {"x":2796,"y":0,"w":896,"h":896},
	"rotated": false,
	"trimmed": false,
	"spriteSourceSize": {"x":0,"y":0,"w":896,"h":896},
	"sourceSize": {"w":896,"h":896}
},
"03_HowToHost_Banner_04.png":
{
	"frame": {"x":3692,"y":0,"w":896,"h":896},
	"rotated": false,
	"trimmed": false,
	"spriteSourceSize": {"x":0,"y":0,"w":896,"h":896},
	"sourceSize": {"w":896,"h":896}
},
"03_HowToHost_Banner_05.png":
{
	"frame": {"x":4588,"y":0,"w":896,"h":896},
	"rotated": false,
	"trimmed": false,
	"spriteSourceSize": {"x":0,"y":0,"w":896,"h":896},
	"sourceSize": {"w":896,"h":896}
},
"03_HowToHost_Banner_06.png":
{
	"frame": {"x":5484,"y":0,"w":896,"h":896},
	"rotated": false,
	"trimmed": false,
	"spriteSourceSize": {"x":0,"y":0,"w":896,"h":896},
	"sourceSize": {"w":896,"h":896}
},
"03_HowToHost_Banner_07.png":
{
	"frame": {"x":6380,"y":0,"w":896,"h":896},
	"rotated": false,
	"trimmed": false,
	"spriteSourceSize": {"x":0,"y":0,"w":896,"h":896},
	"sourceSize": {"w":896,"h":896}
},
"03_HowToHost_Banner_08.png":
{
	"frame": {"x":7276,"y":0,"w":896,"h":896},
	"rotated": false,
	"trimmed": false,
	"spriteSourceSize": {"x":0,"y":0,"w":896,"h":896},
	"sourceSize": {"w":896,"h":896}
},
"03_HowToHost_Banner_09.png":
{
	"frame": {"x":0,"y":1004,"w":896,"h":896},
	"rotated": false,
	"trimmed": false,
	"spriteSourceSize": {"x":0,"y":0,"w":896,"h":896},
	"sourceSize": {"w":896,"h":896}
},
"03_HowToHost_Banner_10.png":
{
	"frame": {"x":896,"y":1004,"w":896,"h":896},
	"rotated": false,
	"trimmed": false,
	"spriteSourceSize": {"x":0,"y":0,"w":896,"h":896},
	"sourceSize": {"w":896,"h":896}
},
"03_HowToHost_Banner_11.png":
{
	"frame": {"x":1792,"y":1004,"w":896,"h":896},
	"rotated": false,
	"trimmed": false,
	"spriteSourceSize": {"x":0,"y":0,"w":896,"h":896},
	"sourceSize": {"w":896,"h":896}
},
"03_HowToHost_Banner_12.png":
{
	"frame": {"x":2688,"y":1004,"w":896,"h":896},
	"rotated": false,
	"trimmed": false,
	"spriteSourceSize": {"x":0,"y":0,"w":896,"h":896},
	"sourceSize": {"w":896,"h":896}
},
"03_HowToHost_Banner_13.png":
{
	"frame": {"x":3584,"y":1004,"w":896,"h":896},
	"rotated": false,
	"trimmed": false,
	"spriteSourceSize": {"x":0,"y":0,"w":896,"h":896},
	"sourceSize": {"w":896,"h":896}
},
"03_HowToHost_Banner_14.png":
{
	"frame": {"x":4480,"y":1004,"w":896,"h":896},
	"rotated": false,
	"trimmed": false,
	"spriteSourceSize": {"x":0,"y":0,"w":896,"h":896},
	"sourceSize": {"w":896,"h":896}
},
"03_HowToHost_Banner_15.png":
{
	"frame": {"x":5376,"y":1004,"w":896,"h":896},
	"rotated": false,
	"trimmed": false,
	"spriteSourceSize": {"x":0,"y":0,"w":896,"h":896},
	"sourceSize": {"w":896,"h":896}
},
"03_HowToHost_Banner_16.png":
{
	"frame": {"x":6272,"y":1004,"w":896,"h":896},
	"rotated": false,
	"trimmed": false,
	"spriteSourceSize": {"x":0,"y":0,"w":896,"h":896},
	"sourceSize": {"w":896,"h":896}
},
"03_HowToHost_Banner_17.png":
{
	"frame": {"x":7168,"y":1004,"w":896,"h":896},
	"rotated": false,
	"trimmed": false,
	"spriteSourceSize": {"x":0,"y":0,"w":896,"h":896},
	"sourceSize": {"w":896,"h":896}
},
"03_HowToHost_Banner_18.png":
{
	"frame": {"x":0,"y":1900,"w":896,"h":896},
	"rotated": false,
	"trimmed": false,
	"spriteSourceSize": {"x":0,"y":0,"w":896,"h":896},
	"sourceSize": {"w":896,"h":896}
},
"03_HowToHost_Banner_19.png":
{
	"frame": {"x":896,"y":1900,"w":896,"h":896},
	"rotated": false,
	"trimmed": false,
	"spriteSourceSize": {"x":0,"y":0,"w":896,"h":896},
	"sourceSize": {"w":896,"h":896}
},
"03_HowToHost_Banner_20.png":
{
	"frame": {"x":1792,"y":1900,"w":896,"h":896},
	"rotated": false,
	"trimmed": false,
	"spriteSourceSize": {"x":0,"y":0,"w":896,"h":896},
	"sourceSize": {"w":896,"h":896}
},
"03_HowToHost_Banner_21.png":
{
	"frame": {"x":2688,"y":1900,"w":896,"h":896},
	"rotated": false,
	"trimmed": false,
	"spriteSourceSize": {"x":0,"y":0,"w":896,"h":896},
	"sourceSize": {"w":896,"h":896}
},
"03_HowToHost_Banner_22.png":
{
	"frame": {"x":3584,"y":1900,"w":896,"h":896},
	"rotated": false,
	"trimmed": false,
	"spriteSourceSize": {"x":0,"y":0,"w":896,"h":896},
	"sourceSize": {"w":896,"h":896}
},
"03_HowToHost_Banner_23.png":
{
	"frame": {"x":4480,"y":1900,"w":896,"h":896},
	"rotated": false,
	"trimmed": false,
	"spriteSourceSize": {"x":0,"y":0,"w":896,"h":896},
	"sourceSize": {"w":896,"h":896}
},
"03_HowToHost_Banner_24.png":
{
	"frame": {"x":5376,"y":1900,"w":896,"h":896},
	"rotated": false,
	"trimmed": false,
	"spriteSourceSize": {"x":0,"y":0,"w":896,"h":896},
	"sourceSize": {"w":896,"h":896}
},
"03_HowToHost_Banner_25.png":
{
	"frame": {"x":6272,"y":1900,"w":896,"h":896},
	"rotated": false,
	"trimmed": false,
	"spriteSourceSize": {"x":0,"y":0,"w":896,"h":896},
	"sourceSize": {"w":896,"h":896}
},
"03_HowToHost_Banner_26.png":
{
	"frame": {"x":7168,"y":1900,"w":896,"h":896},
	"rotated": false,
	"trimmed": false,
	"spriteSourceSize": {"x":0,"y":0,"w":896,"h":896},
	"sourceSize": {"w":896,"h":896}
},
"03_HowToHost_Banner_27.png":
{
	"frame": {"x":0,"y":2796,"w":896,"h":896},
	"rotated": false,
	"trimmed": false,
	"spriteSourceSize": {"x":0,"y":0,"w":896,"h":896},
	"sourceSize": {"w":896,"h":896}
},
"03_HowToHost_Banner_28.png":
{
	"frame": {"x":896,"y":2796,"w":896,"h":896},
	"rotated": false,
	"trimmed": false,
	"spriteSourceSize": {"x":0,"y":0,"w":896,"h":896},
	"sourceSize": {"w":896,"h":896}
},
"03_HowToHost_Banner_29.png":
{
	"frame": {"x":1792,"y":2796,"w":896,"h":896},
	"rotated": false,
	"trimmed": false,
	"spriteSourceSize": {"x":0,"y":0,"w":896,"h":896},
	"sourceSize": {"w":896,"h":896}
},
"03_HowToHost_Banner_30.png":
{
	"frame": {"x":2688,"y":2796,"w":896,"h":896},
	"rotated": false,
	"trimmed": false,
	"spriteSourceSize": {"x":0,"y":0,"w":896,"h":896},
	"sourceSize": {"w":896,"h":896}
},
"03_HowToHost_Banner_31.png":
{
	"frame": {"x":3584,"y":2796,"w":896,"h":896},
	"rotated": false,
	"trimmed": false,
	"spriteSourceSize": {"x":0,"y":0,"w":896,"h":896},
	"sourceSize": {"w":896,"h":896}
},
"03_HowToHost_Banner_32.png":
{
	"frame": {"x":4480,"y":2796,"w":896,"h":896},
	"rotated": false,
	"trimmed": false,
	"spriteSourceSize": {"x":0,"y":0,"w":896,"h":896},
	"sourceSize": {"w":896,"h":896}
},
"03_HowToHost_Banner_33.png":
{
	"frame": {"x":5376,"y":2796,"w":896,"h":896},
	"rotated": false,
	"trimmed": false,
	"spriteSourceSize": {"x":0,"y":0,"w":896,"h":896},
	"sourceSize": {"w":896,"h":896}
},
"03_HowToHost_Banner_34.png":
{
	"frame": {"x":6272,"y":2796,"w":896,"h":896},
	"rotated": false,
	"trimmed": false,
	"spriteSourceSize": {"x":0,"y":0,"w":896,"h":896},
	"sourceSize": {"w":896,"h":896}
},
"03_HowToHost_Banner_35.png":
{
	"frame": {"x":7168,"y":2796,"w":896,"h":896},
	"rotated": false,
	"trimmed": false,
	"spriteSourceSize": {"x":0,"y":0,"w":896,"h":896},
	"sourceSize": {"w":896,"h":896}
},
"03_HowToHost_Banner_36.png":
{
	"frame": {"x":0,"y":3692,"w":896,"h":896},
	"rotated": false,
	"trimmed": false,
	"spriteSourceSize": {"x":0,"y":0,"w":896,"h":896},
	"sourceSize": {"w":896,"h":896}
},
"03_HowToHost_Banner_37.png":
{
	"frame": {"x":896,"y":3692,"w":896,"h":896},
	"rotated": false,
	"trimmed": false,
	"spriteSourceSize": {"x":0,"y":0,"w":896,"h":896},
	"sourceSize": {"w":896,"h":896}
},
"03_HowToHost_Banner_38.png":
{
	"frame": {"x":1792,"y":3692,"w":896,"h":896},
	"rotated": false,
	"trimmed": false,
	"spriteSourceSize": {"x":0,"y":0,"w":896,"h":896},
	"sourceSize": {"w":896,"h":896}
},
"03_HowToHost_Banner_39.png":
{
	"frame": {"x":2688,"y":3692,"w":896,"h":896},
	"rotated": false,
	"trimmed": false,
	"spriteSourceSize": {"x":0,"y":0,"w":896,"h":896},
	"sourceSize": {"w":896,"h":896}
},
"03_HowToHost_Banner_40.png":
{
	"frame": {"x":3584,"y":3692,"w":896,"h":896},
	"rotated": false,
	"trimmed": false,
	"spriteSourceSize": {"x":0,"y":0,"w":896,"h":896},
	"sourceSize": {"w":896,"h":896}
}},
"meta": {
	"app": "Adobe Flash Professional",
	"version": "15.0.0.173",
	"image": "03_HowToHost_Banner.png",
	"format": "RGBA8888",
	"size": {"w":8192,"h":8192},
	"scale": "1"
}
}
