{"frames": {

"05_SaveAMate_00.png":
{
	"frame": {"x":0,"y":0,"w":232,"h":232},
	"rotated": false,
	"trimmed": false,
	"spriteSourceSize": {"x":0,"y":0,"w":232,"h":232},
	"sourceSize": {"w":232,"h":232}
},
"05_SaveAMate_01.png":
{
	"frame": {"x":232,"y":0,"w":232,"h":232},
	"rotated": false,
	"trimmed": false,
	"spriteSourceSize": {"x":0,"y":0,"w":232,"h":232},
	"sourceSize": {"w":232,"h":232}
},
"05_SaveAMate_02.png":
{
	"frame": {"x":464,"y":0,"w":232,"h":232},
	"rotated": false,
	"trimmed": false,
	"spriteSourceSize": {"x":0,"y":0,"w":232,"h":232},
	"sourceSize": {"w":232,"h":232}
},
"05_SaveAMate_03.png":
{
	"frame": {"x":696,"y":0,"w":232,"h":232},
	"rotated": false,
	"trimmed": false,
	"spriteSourceSize": {"x":0,"y":0,"w":232,"h":232},
	"sourceSize": {"w":232,"h":232}
},
"05_SaveAMate_04.png":
{
	"frame": {"x":928,"y":0,"w":232,"h":232},
	"rotated": false,
	"trimmed": false,
	"spriteSourceSize": {"x":0,"y":0,"w":232,"h":232},
	"sourceSize": {"w":232,"h":232}
},
"05_SaveAMate_05.png":
{
	"frame": {"x":1160,"y":0,"w":232,"h":232},
	"rotated": false,
	"trimmed": false,
	"spriteSourceSize": {"x":0,"y":0,"w":232,"h":232},
	"sourceSize": {"w":232,"h":232}
},
"05_SaveAMate_06.png":
{
	"frame": {"x":1392,"y":0,"w":232,"h":232},
	"rotated": false,
	"trimmed": false,
	"spriteSourceSize": {"x":0,"y":0,"w":232,"h":232},
	"sourceSize": {"w":232,"h":232}
},
"05_SaveAMate_07.png":
{
	"frame": {"x":1624,"y":0,"w":232,"h":232},
	"rotated": false,
	"trimmed": false,
	"spriteSourceSize": {"x":0,"y":0,"w":232,"h":232},
	"sourceSize": {"w":232,"h":232}
},
"05_SaveAMate_08.png":
{
	"frame": {"x":0,"y":232,"w":232,"h":232},
	"rotated": false,
	"trimmed": false,
	"spriteSourceSize": {"x":0,"y":0,"w":232,"h":232},
	"sourceSize": {"w":232,"h":232}
},
"05_SaveAMate_09.png":
{
	"frame": {"x":232,"y":232,"w":232,"h":232},
	"rotated": false,
	"trimmed": false,
	"spriteSourceSize": {"x":0,"y":0,"w":232,"h":232},
	"sourceSize": {"w":232,"h":232}
},
"05_SaveAMate_10.png":
{
	"frame": {"x":464,"y":232,"w":232,"h":232},
	"rotated": false,
	"trimmed": false,
	"spriteSourceSize": {"x":0,"y":0,"w":232,"h":232},
	"sourceSize": {"w":232,"h":232}
},
"05_SaveAMate_11.png":
{
	"frame": {"x":696,"y":232,"w":232,"h":232},
	"rotated": false,
	"trimmed": false,
	"spriteSourceSize": {"x":0,"y":0,"w":232,"h":232},
	"sourceSize": {"w":232,"h":232}
},
"05_SaveAMate_12.png":
{
	"frame": {"x":928,"y":232,"w":232,"h":232},
	"rotated": false,
	"trimmed": false,
	"spriteSourceSize": {"x":0,"y":0,"w":232,"h":232},
	"sourceSize": {"w":232,"h":232}
},
"05_SaveAMate_13.png":
{
	"frame": {"x":1160,"y":232,"w":232,"h":232},
	"rotated": false,
	"trimmed": false,
	"spriteSourceSize": {"x":0,"y":0,"w":232,"h":232},
	"sourceSize": {"w":232,"h":232}
},
"05_SaveAMate_14.png":
{
	"frame": {"x":1392,"y":232,"w":232,"h":232},
	"rotated": false,
	"trimmed": false,
	"spriteSourceSize": {"x":0,"y":0,"w":232,"h":232},
	"sourceSize": {"w":232,"h":232}
},
"05_SaveAMate_15.png":
{
	"frame": {"x":1624,"y":232,"w":232,"h":232},
	"rotated": false,
	"trimmed": false,
	"spriteSourceSize": {"x":0,"y":0,"w":232,"h":232},
	"sourceSize": {"w":232,"h":232}
},
"05_SaveAMate_16.png":
{
	"frame": {"x":0,"y":464,"w":232,"h":232},
	"rotated": false,
	"trimmed": false,
	"spriteSourceSize": {"x":0,"y":0,"w":232,"h":232},
	"sourceSize": {"w":232,"h":232}
},
"05_SaveAMate_17.png":
{
	"frame": {"x":232,"y":464,"w":232,"h":232},
	"rotated": false,
	"trimmed": false,
	"spriteSourceSize": {"x":0,"y":0,"w":232,"h":232},
	"sourceSize": {"w":232,"h":232}
},
"05_SaveAMate_18.png":
{
	"frame": {"x":464,"y":464,"w":232,"h":232},
	"rotated": false,
	"trimmed": false,
	"spriteSourceSize": {"x":0,"y":0,"w":232,"h":232},
	"sourceSize": {"w":232,"h":232}
},
"05_SaveAMate_19.png":
{
	"frame": {"x":696,"y":464,"w":232,"h":232},
	"rotated": false,
	"trimmed": false,
	"spriteSourceSize": {"x":0,"y":0,"w":232,"h":232},
	"sourceSize": {"w":232,"h":232}
},
"05_SaveAMate_20.png":
{
	"frame": {"x":928,"y":464,"w":232,"h":232},
	"rotated": false,
	"trimmed": false,
	"spriteSourceSize": {"x":0,"y":0,"w":232,"h":232},
	"sourceSize": {"w":232,"h":232}
},
"05_SaveAMate_21.png":
{
	"frame": {"x":1160,"y":464,"w":232,"h":232},
	"rotated": false,
	"trimmed": false,
	"spriteSourceSize": {"x":0,"y":0,"w":232,"h":232},
	"sourceSize": {"w":232,"h":232}
},
"05_SaveAMate_22.png":
{
	"frame": {"x":1392,"y":464,"w":232,"h":232},
	"rotated": false,
	"trimmed": false,
	"spriteSourceSize": {"x":0,"y":0,"w":232,"h":232},
	"sourceSize": {"w":232,"h":232}
},
"05_SaveAMate_23.png":
{
	"frame": {"x":1624,"y":464,"w":232,"h":232},
	"rotated": false,
	"trimmed": false,
	"spriteSourceSize": {"x":0,"y":0,"w":232,"h":232},
	"sourceSize": {"w":232,"h":232}
},
"05_SaveAMate_24.png":
{
	"frame": {"x":0,"y":696,"w":232,"h":232},
	"rotated": false,
	"trimmed": false,
	"spriteSourceSize": {"x":0,"y":0,"w":232,"h":232},
	"sourceSize": {"w":232,"h":232}
},
"05_SaveAMate_25.png":
{
	"frame": {"x":232,"y":696,"w":232,"h":232},
	"rotated": false,
	"trimmed": false,
	"spriteSourceSize": {"x":0,"y":0,"w":232,"h":232},
	"sourceSize": {"w":232,"h":232}
},
"05_SaveAMate_26.png":
{
	"frame": {"x":464,"y":696,"w":232,"h":232},
	"rotated": false,
	"trimmed": false,
	"spriteSourceSize": {"x":0,"y":0,"w":232,"h":232},
	"sourceSize": {"w":232,"h":232}
},
"05_SaveAMate_27.png":
{
	"frame": {"x":696,"y":696,"w":232,"h":232},
	"rotated": false,
	"trimmed": false,
	"spriteSourceSize": {"x":0,"y":0,"w":232,"h":232},
	"sourceSize": {"w":232,"h":232}
},
"05_SaveAMate_28.png":
{
	"frame": {"x":928,"y":696,"w":232,"h":232},
	"rotated": false,
	"trimmed": false,
	"spriteSourceSize": {"x":0,"y":0,"w":232,"h":232},
	"sourceSize": {"w":232,"h":232}
},
"05_SaveAMate_29.png":
{
	"frame": {"x":1160,"y":696,"w":232,"h":232},
	"rotated": false,
	"trimmed": false,
	"spriteSourceSize": {"x":0,"y":0,"w":232,"h":232},
	"sourceSize": {"w":232,"h":232}
},
"05_SaveAMate_30.png":
{
	"frame": {"x":1392,"y":696,"w":232,"h":232},
	"rotated": false,
	"trimmed": false,
	"spriteSourceSize": {"x":0,"y":0,"w":232,"h":232},
	"sourceSize": {"w":232,"h":232}
},
"05_SaveAMate_31.png":
{
	"frame": {"x":1624,"y":696,"w":232,"h":232},
	"rotated": false,
	"trimmed": false,
	"spriteSourceSize": {"x":0,"y":0,"w":232,"h":232},
	"sourceSize": {"w":232,"h":232}
},
"05_SaveAMate_32.png":
{
	"frame": {"x":0,"y":928,"w":232,"h":232},
	"rotated": false,
	"trimmed": false,
	"spriteSourceSize": {"x":0,"y":0,"w":232,"h":232},
	"sourceSize": {"w":232,"h":232}
},
"05_SaveAMate_33.png":
{
	"frame": {"x":232,"y":928,"w":232,"h":232},
	"rotated": false,
	"trimmed": false,
	"spriteSourceSize": {"x":0,"y":0,"w":232,"h":232},
	"sourceSize": {"w":232,"h":232}
},
"05_SaveAMate_34.png":
{
	"frame": {"x":464,"y":928,"w":232,"h":232},
	"rotated": false,
	"trimmed": false,
	"spriteSourceSize": {"x":0,"y":0,"w":232,"h":232},
	"sourceSize": {"w":232,"h":232}
},
"05_SaveAMate_35.png":
{
	"frame": {"x":696,"y":928,"w":232,"h":232},
	"rotated": false,
	"trimmed": false,
	"spriteSourceSize": {"x":0,"y":0,"w":232,"h":232},
	"sourceSize": {"w":232,"h":232}
},
"05_SaveAMate_36.png":
{
	"frame": {"x":928,"y":928,"w":232,"h":232},
	"rotated": false,
	"trimmed": false,
	"spriteSourceSize": {"x":0,"y":0,"w":232,"h":232},
	"sourceSize": {"w":232,"h":232}
},
"05_SaveAMate_37.png":
{
	"frame": {"x":1160,"y":928,"w":232,"h":232},
	"rotated": false,
	"trimmed": false,
	"spriteSourceSize": {"x":0,"y":0,"w":232,"h":232},
	"sourceSize": {"w":232,"h":232}
},
"05_SaveAMate_38.png":
{
	"frame": {"x":1392,"y":928,"w":232,"h":232},
	"rotated": false,
	"trimmed": false,
	"spriteSourceSize": {"x":0,"y":0,"w":232,"h":232},
	"sourceSize": {"w":232,"h":232}
},
"05_SaveAMate_39.png":
{
	"frame": {"x":1624,"y":928,"w":232,"h":232},
	"rotated": false,
	"trimmed": false,
	"spriteSourceSize": {"x":0,"y":0,"w":232,"h":232},
	"sourceSize": {"w":232,"h":232}
},
"05_SaveAMate_40.png":
{
	"frame": {"x":0,"y":1160,"w":232,"h":232},
	"rotated": false,
	"trimmed": false,
	"spriteSourceSize": {"x":0,"y":0,"w":232,"h":232},
	"sourceSize": {"w":232,"h":232}
},
"05_SaveAMate_41.png":
{
	"frame": {"x":232,"y":1160,"w":232,"h":232},
	"rotated": false,
	"trimmed": false,
	"spriteSourceSize": {"x":0,"y":0,"w":232,"h":232},
	"sourceSize": {"w":232,"h":232}
},
"05_SaveAMate_42.png":
{
	"frame": {"x":464,"y":1160,"w":232,"h":232},
	"rotated": false,
	"trimmed": false,
	"spriteSourceSize": {"x":0,"y":0,"w":232,"h":232},
	"sourceSize": {"w":232,"h":232}
},
"05_SaveAMate_43.png":
{
	"frame": {"x":696,"y":1160,"w":232,"h":232},
	"rotated": false,
	"trimmed": false,
	"spriteSourceSize": {"x":0,"y":0,"w":232,"h":232},
	"sourceSize": {"w":232,"h":232}
},
"05_SaveAMate_44.png":
{
	"frame": {"x":928,"y":1160,"w":232,"h":232},
	"rotated": false,
	"trimmed": false,
	"spriteSourceSize": {"x":0,"y":0,"w":232,"h":232},
	"sourceSize": {"w":232,"h":232}
},
"05_SaveAMate_45.png":
{
	"frame": {"x":1160,"y":1160,"w":232,"h":232},
	"rotated": false,
	"trimmed": false,
	"spriteSourceSize": {"x":0,"y":0,"w":232,"h":232},
	"sourceSize": {"w":232,"h":232}
},
"05_SaveAMate_46.png":
{
	"frame": {"x":1392,"y":1160,"w":232,"h":232},
	"rotated": false,
	"trimmed": false,
	"spriteSourceSize": {"x":0,"y":0,"w":232,"h":232},
	"sourceSize": {"w":232,"h":232}
},
"05_SaveAMate_47.png":
{
	"frame": {"x":1624,"y":1160,"w":232,"h":232},
	"rotated": false,
	"trimmed": false,
	"spriteSourceSize": {"x":0,"y":0,"w":232,"h":232},
	"sourceSize": {"w":232,"h":232}
},
"05_SaveAMate_48.png":
{
	"frame": {"x":0,"y":1392,"w":232,"h":232},
	"rotated": false,
	"trimmed": false,
	"spriteSourceSize": {"x":0,"y":0,"w":232,"h":232},
	"sourceSize": {"w":232,"h":232}
},
"05_SaveAMate_49.png":
{
	"frame": {"x":0,"y":0,"w":232,"h":232},
	"rotated": false,
	"trimmed": false,
	"spriteSourceSize": {"x":0,"y":0,"w":232,"h":232},
	"sourceSize": {"w":232,"h":232}
}},
"meta": {
	"app": "Adobe Flash Professional",
	"version": "15.0.0.173",
	"image": "05_SaveAMate.png",
	"format": "RGBA8888",
	"size": {"w":2048,"h":2048},
	"scale": "1"
}
}
